dnamite/__init__.py
dnamite/datasets/__init__.py
dnamite/datasets/data_loaders.py
dnamite/loss_fns/__init__.py
dnamite/loss_fns/loss_fns.py
dnamite/models/__init__.py
dnamite/models/base_model.py
dnamite/models/base_single_split.py
dnamite/models/binary_classifier.py
dnamite/models/regressor.py
dnamite/models/survival.py
dnamite/utils/__init__.py
dnamite/utils/logging.py
dnamite/utils/utils.py
dnamite-1.0.8.dist-info/licenses/LICENSE
docs/source/conf.py
dnamite-1.0.8.dist-info/METADATA
dnamite-1.0.8.dist-info/WHEEL
dnamite-1.0.8.dist-info/top_level.txt
dnamite-1.0.8.dist-info/RECORD
