Metadata-Version: 2.4
Name: dnamite
Version: 1.0.8
Summary: Implementation of DNAMite, an interpretable model for survival analysis and more.
Author-email: Mike Van Ness <mvanness354@gmail.com>
Classifier: Programming Language :: Python :: 3
Classifier: License :: OSI Approved :: MIT License
Classifier: Operating System :: OS Independent
Requires-Python: >=3.7
License-File: LICENSE
Requires-Dist: numpy>=1.23.5
Requires-Dist: pandas>=1.5.0
Requires-Dist: PyYAML>=6.0.2
Requires-Dist: scikit_learn>=1.3.2
Requires-Dist: scikit_survival>=0.22.2
Requires-Dist: torch>=1.13.1
Requires-Dist: tqdm>=4.64.1
Requires-Dist: interpret>=0.4.2
Requires-Dist: interpret_core>=0.4.2
Requires-Dist: matplotlib>=3.6.2
Requires-Dist: seaborn>=0.13.2
Dynamic: license-file
